{
  "@context": "http://iiif.io/api/presentation/2/context.json",
  "@id": "http://aadhum.mith.us/manifests/manifest.json",
  "@type": "sc:Manifest",
  "label": "Bearden, Romare - Oral History Interview with David C. Driskell, 2001-2002",
  "metadata": [
    {
      "label": "",
      "value": ""
    },
    {
      "label": "Returned in Box",
      "value": "5"
    },
    {
      "label": "Extent",
      "value": "22"
    },
    {
      "label": "Geographic coverage",
      "value": ""
    },
    {
      "label": "Archival Collection",
      "value": "David C. Driskell Papers"
    },
    {
      "label": "Box",
      "value": "3"
    },
    {
      "label": "Temporal Coverage",
      "value": ""
    },
    {
      "label": "Contributor Role",
      "value": ""
    },
    {
      "label": "RequestedActions",
      "value": ""
    },
    {
      "label": "Date Attribute",
      "value": "2001-2002"
    },
    {
      "label": "Title",
      "value": "Bearden, Romare - Oral History Interview with David C. Driskell, 2001-2002"
    },
    {
      "label": "Filename from vendor",
      "value": "mdu-062692a"
    },
    {
      "label": "Creator",
      "value": ""
    },
    {
      "label": "Rights Holder",
      "value": ""
    },
    {
      "label": "Rights",
      "value": ""
    },
    {
      "label": "MediaType",
      "value": "Text"
    },
    {
      "label": "Description/Summary",
      "value": "Transcript of an oral history interview conducted on November 30, 2001 of Romare Bearden by David C. Driskell and letter from Driskell with corrections."
    },
    {
      "label": "Shipment Box",
      "value": "Driskell_Box5 "
    },
    {
      "label": "AccessionNumber",
      "value": "MS2011.01"
    },
    {
      "label": "Subseries",
      "value": ""
    },
    {
      "label": "Date or Date range",
      "value": "2001-2002"
    },
    {
      "label": "Creator Role",
      "value": ""
    },
    {
      "label": "Notes",
      "value": ""
    },
    {
      "label": "Reshelved",
      "value": "yes"
    },
    {
      "label": "Format",
      "value": ""
    },
    {
      "label": "Folder",
      "value": "10"
    },
    {
      "label": "Alternate Title",
      "value": ""
    },
    {
      "label": "Series",
      "value": "Series 5: Artists and Individuals"
    },
    {
      "label": "Subject",
      "value": ""
    },
    {
      "label": "Changed on Drive",
      "value": "yes"
    },
    {
      "label": "PersonalSubject URI",
      "value": ""
    },
    {
      "label": "Provider/Publisher",
      "value": ""
    },
    {
      "label": "CorpSubject URI",
      "value": ""
    },
    {
      "label": "FilenameRoot",
      "value": "mdu-062615"
    },
    {
      "label": "PersonalSubject",
      "value": ""
    },
    {
      "label": "Contributor",
      "value": ""
    },
    {
      "label": "Item",
      "value": ""
    },
    {
      "label": "CorpSubject",
      "value": ""
    },
    {
      "label": "InspectionNotes",
      "value": ""
    },
    {
      "label": "Subject URIs",
      "value": ""
    },
    {
      "label": "Filename adjustment",
      "value": "mdu-062615"
    },
    {
      "label": "DateAndInitials",
      "value": ""
    },
    {
      "label": "Language",
      "value": ""
    },
    {
      "label": "Identifier",
      "value": ""
    }
  ],
  "description": "Transcript of an oral history interview conducted on November 30, 2001 of Romare Bearden by David C. Driskell and letter from Driskell with corrections.",
  "sequences": [
    {
      "@type": "sc:Sequence",
      "canvases": [
        {
          "@id": "http://aadhum.mith.us/mdu/062615/1/canvas",
          "@type": "sc:Canvas",
          "label": "0001",
          "thumbnail": {
            "@id": "http://aadhum.mith.us/images/1f55da84dc064077d5d63cd1abf4fad0/full/424,/0/default.jpg",
            "service": {
              "@context": "http://iiif.io/api/image/2/context.json",
              "@id": "http://aadhum.mith.us/images/1f55da84dc064077d5d63cd1abf4fad0",
              "profile": [
                "http://iiif.io/api/image/2/level0.json",
                {
                  "qualities": [
                    "default"
                  ],
                  "formats": [
                    "jpg"
                  ]
                }
              ]
            }
          },
          "height": 4396,
          "width": 3395,
          "images": [
            {
              "@id": "http://aadhum.mith.us/mdu/062615/1/annotation",
              "@type": "oa:Annotation",
              "motivation": "sc:painting",
              "resource": {
                "@id": "http://aadhum.mith.us/images/1f55da84dc064077d5d63cd1abf4fad0/full/full/0/default.jpg",
                "@type": "dctypes:Image",
                "format": "image/jpeg",
                "height": 4396,
                "width": 3395,
                "service": {
                  "@context": "http://iiif.io/api/image/2/context.json",
                  "@id": "http://aadhum.mith.us/images/1f55da84dc064077d5d63cd1abf4fad0",
                  "profile": "http://iiif.io/api/image/2/level0.json"
                }
              },
              "on": "http://aadhum.mith.us/mdu/062615/1/canvas"
            }
          ]
        },
        {
          "@id": "http://aadhum.mith.us/mdu/062615/2/canvas",
          "@type": "sc:Canvas",
          "label": "0002",
          "thumbnail": {
            "@id": "http://aadhum.mith.us/images/6f9f225a69b28a430ea12d09c52359d2/full/421,/0/default.jpg",
            "service": {
              "@context": "http://iiif.io/api/image/2/context.json",
              "@id": "http://aadhum.mith.us/images/6f9f225a69b28a430ea12d09c52359d2",
              "profile": [
                "http://iiif.io/api/image/2/level0.json",
                {
                  "qualities": [
                    "default"
                  ],
                  "formats": [
                    "jpg"
                  ]
                }
              ]
            }
          },
          "height": 4398,
          "width": 3370,
          "images": [
            {
              "@id": "http://aadhum.mith.us/mdu/062615/2/annotation",
              "@type": "oa:Annotation",
              "motivation": "sc:painting",
              "resource": {
                "@id": "http://aadhum.mith.us/images/6f9f225a69b28a430ea12d09c52359d2/full/full/0/default.jpg",
                "@type": "dctypes:Image",
                "format": "image/jpeg",
                "height": 4398,
                "width": 3370,
                "service": {
                  "@context": "http://iiif.io/api/image/2/context.json",
                  "@id": "http://aadhum.mith.us/images/6f9f225a69b28a430ea12d09c52359d2",
                  "profile": "http://iiif.io/api/image/2/level0.json"
                }
              },
              "on": "http://aadhum.mith.us/mdu/062615/2/canvas"
            }
          ]
        },
        {
          "@id": "http://aadhum.mith.us/mdu/062615/3/canvas",
          "@type": "sc:Canvas",
          "label": "0003",
          "thumbnail": {
            "@id": "http://aadhum.mith.us/images/3e7c27e43436fde01acc89770a3208f5/full/423,/0/default.jpg",
            "service": {
              "@context": "http://iiif.io/api/image/2/context.json",
              "@id": "http://aadhum.mith.us/images/3e7c27e43436fde01acc89770a3208f5",
              "profile": [
                "http://iiif.io/api/image/2/level0.json",
                {
                  "qualities": [
                    "default"
                  ],
                  "formats": [
                    "jpg"
                  ]
                }
              ]
            }
          },
          "height": 4382,
          "width": 3384,
          "images": [
            {
              "@id": "http://aadhum.mith.us/mdu/062615/3/annotation",
              "@type": "oa:Annotation",
              "motivation": "sc:painting",
              "resource": {
                "@id": "http://aadhum.mith.us/images/3e7c27e43436fde01acc89770a3208f5/full/full/0/default.jpg",
                "@type": "dctypes:Image",
                "format": "image/jpeg",
                "height": 4382,
                "width": 3384,
                "service": {
                  "@context": "http://iiif.io/api/image/2/context.json",
                  "@id": "http://aadhum.mith.us/images/3e7c27e43436fde01acc89770a3208f5",
                  "profile": "http://iiif.io/api/image/2/level0.json"
                }
              },
              "on": "http://aadhum.mith.us/mdu/062615/3/canvas"
            }
          ]
        },
        {
          "@id": "http://aadhum.mith.us/mdu/062615/4/canvas",
          "@type": "sc:Canvas",
          "label": "0004",
          "thumbnail": {
            "@id": "http://aadhum.mith.us/images/4552b9aae1c5a8130bcecab00d28dc37/full/421,/0/default.jpg",
            "service": {
              "@context": "http://iiif.io/api/image/2/context.json",
              "@id": "http://aadhum.mith.us/images/4552b9aae1c5a8130bcecab00d28dc37",
              "profile": [
                "http://iiif.io/api/image/2/level0.json",
                {
                  "qualities": [
                    "default"
                  ],
                  "formats": [
                    "jpg"
                  ]
                }
              ]
            }
          },
          "height": 4396,
          "width": 3368,
          "images": [
            {
              "@id": "http://aadhum.mith.us/mdu/062615/4/annotation",
              "@type": "oa:Annotation",
              "motivation": "sc:painting",
              "resource": {
                "@id": "http://aadhum.mith.us/images/4552b9aae1c5a8130bcecab00d28dc37/full/full/0/default.jpg",
                "@type": "dctypes:Image",
                "format": "image/jpeg",
                "height": 4396,
                "width": 3368,
                "service": {
                  "@context": "http://iiif.io/api/image/2/context.json",
                  "@id": "http://aadhum.mith.us/images/4552b9aae1c5a8130bcecab00d28dc37",
                  "profile": "http://iiif.io/api/image/2/level0.json"
                }
              },
              "on": "http://aadhum.mith.us/mdu/062615/4/canvas"
            }
          ]
        },
        {
          "@id": "http://aadhum.mith.us/mdu/062615/5/canvas",
          "@type": "sc:Canvas",
          "label": "0005",
          "thumbnail": {
            "@id": "http://aadhum.mith.us/images/241b126f040f155b9800f117da550380/full/422,/0/default.jpg",
            "service": {
              "@context": "http://iiif.io/api/image/2/context.json",
              "@id": "http://aadhum.mith.us/images/241b126f040f155b9800f117da550380",
              "profile": [
                "http://iiif.io/api/image/2/level0.json",
                {
                  "qualities": [
                    "default"
                  ],
                  "formats": [
                    "jpg"
                  ]
                }
              ]
            }
          },
          "height": 4392,
          "width": 3378,
          "images": [
            {
              "@id": "http://aadhum.mith.us/mdu/062615/5/annotation",
              "@type": "oa:Annotation",
              "motivation": "sc:painting",
              "resource": {
                "@id": "http://aadhum.mith.us/images/241b126f040f155b9800f117da550380/full/full/0/default.jpg",
                "@type": "dctypes:Image",
                "format": "image/jpeg",
                "height": 4392,
                "width": 3378,
                "service": {
                  "@context": "http://iiif.io/api/image/2/context.json",
                  "@id": "http://aadhum.mith.us/images/241b126f040f155b9800f117da550380",
                  "profile": "http://iiif.io/api/image/2/level0.json"
                }
              },
              "on": "http://aadhum.mith.us/mdu/062615/5/canvas"
            }
          ]
        },
        {
          "@id": "http://aadhum.mith.us/mdu/062615/6/canvas",
          "@type": "sc:Canvas",
          "label": "0006",
          "thumbnail": {
            "@id": "http://aadhum.mith.us/images/c275af5d597fc767b4e7ee9f3ac50312/full/421,/0/default.jpg",
            "service": {
              "@context": "http://iiif.io/api/image/2/context.json",
              "@id": "http://aadhum.mith.us/images/c275af5d597fc767b4e7ee9f3ac50312",
              "profile": [
                "http://iiif.io/api/image/2/level0.json",
                {
                  "qualities": [
                    "default"
                  ],
                  "formats": [
                    "jpg"
                  ]
                }
              ]
            }
          },
          "height": 4398,
          "width": 3370,
          "images": [
            {
              "@id": "http://aadhum.mith.us/mdu/062615/6/annotation",
              "@type": "oa:Annotation",
              "motivation": "sc:painting",
              "resource": {
                "@id": "http://aadhum.mith.us/images/c275af5d597fc767b4e7ee9f3ac50312/full/full/0/default.jpg",
                "@type": "dctypes:Image",
                "format": "image/jpeg",
                "height": 4398,
                "width": 3370,
                "service": {
                  "@context": "http://iiif.io/api/image/2/context.json",
                  "@id": "http://aadhum.mith.us/images/c275af5d597fc767b4e7ee9f3ac50312",
                  "profile": "http://iiif.io/api/image/2/level0.json"
                }
              },
              "on": "http://aadhum.mith.us/mdu/062615/6/canvas"
            }
          ]
        },
        {
          "@id": "http://aadhum.mith.us/mdu/062615/7/canvas",
          "@type": "sc:Canvas",
          "label": "0007",
          "thumbnail": {
            "@id": "http://aadhum.mith.us/images/ced54ede765f7012b75b41d70b6439e5/full/421,/0/default.jpg",
            "service": {
              "@context": "http://iiif.io/api/image/2/context.json",
              "@id": "http://aadhum.mith.us/images/ced54ede765f7012b75b41d70b6439e5",
              "profile": [
                "http://iiif.io/api/image/2/level0.json",
                {
                  "qualities": [
                    "default"
                  ],
                  "formats": [
                    "jpg"
                  ]
                }
              ]
            }
          },
          "height": 4398,
          "width": 3364,
          "images": [
            {
              "@id": "http://aadhum.mith.us/mdu/062615/7/annotation",
              "@type": "oa:Annotation",
              "motivation": "sc:painting",
              "resource": {
                "@id": "http://aadhum.mith.us/images/ced54ede765f7012b75b41d70b6439e5/full/full/0/default.jpg",
                "@type": "dctypes:Image",
                "format": "image/jpeg",
                "height": 4398,
                "width": 3364,
                "service": {
                  "@context": "http://iiif.io/api/image/2/context.json",
                  "@id": "http://aadhum.mith.us/images/ced54ede765f7012b75b41d70b6439e5",
                  "profile": "http://iiif.io/api/image/2/level0.json"
                }
              },
              "on": "http://aadhum.mith.us/mdu/062615/7/canvas"
            }
          ]
        },
        {
          "@id": "http://aadhum.mith.us/mdu/062615/8/canvas",
          "@type": "sc:Canvas",
          "label": "0008",
          "thumbnail": {
            "@id": "http://aadhum.mith.us/images/6838c4fcfd1f7f01c06981c0c130bcfa/full/422,/0/default.jpg",
            "service": {
              "@context": "http://iiif.io/api/image/2/context.json",
              "@id": "http://aadhum.mith.us/images/6838c4fcfd1f7f01c06981c0c130bcfa",
              "profile": [
                "http://iiif.io/api/image/2/level0.json",
                {
                  "qualities": [
                    "default"
                  ],
                  "formats": [
                    "jpg"
                  ]
                }
              ]
            }
          },
          "height": 4396,
          "width": 3372,
          "images": [
            {
              "@id": "http://aadhum.mith.us/mdu/062615/8/annotation",
              "@type": "oa:Annotation",
              "motivation": "sc:painting",
              "resource": {
                "@id": "http://aadhum.mith.us/images/6838c4fcfd1f7f01c06981c0c130bcfa/full/full/0/default.jpg",
                "@type": "dctypes:Image",
                "format": "image/jpeg",
                "height": 4396,
                "width": 3372,
                "service": {
                  "@context": "http://iiif.io/api/image/2/context.json",
                  "@id": "http://aadhum.mith.us/images/6838c4fcfd1f7f01c06981c0c130bcfa",
                  "profile": "http://iiif.io/api/image/2/level0.json"
                }
              },
              "on": "http://aadhum.mith.us/mdu/062615/8/canvas"
            }
          ]
        },
        {
          "@id": "http://aadhum.mith.us/mdu/062615/9/canvas",
          "@type": "sc:Canvas",
          "label": "0009",
          "thumbnail": {
            "@id": "http://aadhum.mith.us/images/2080e82d02d62dd9840aedec01d04496/full/422,/0/default.jpg",
            "service": {
              "@context": "http://iiif.io/api/image/2/context.json",
              "@id": "http://aadhum.mith.us/images/2080e82d02d62dd9840aedec01d04496",
              "profile": [
                "http://iiif.io/api/image/2/level0.json",
                {
                  "qualities": [
                    "default"
                  ],
                  "formats": [
                    "jpg"
                  ]
                }
              ]
            }
          },
          "height": 4404,
          "width": 3374,
          "images": [
            {
              "@id": "http://aadhum.mith.us/mdu/062615/9/annotation",
              "@type": "oa:Annotation",
              "motivation": "sc:painting",
              "resource": {
                "@id": "http://aadhum.mith.us/images/2080e82d02d62dd9840aedec01d04496/full/full/0/default.jpg",
                "@type": "dctypes:Image",
                "format": "image/jpeg",
                "height": 4404,
                "width": 3374,
                "service": {
                  "@context": "http://iiif.io/api/image/2/context.json",
                  "@id": "http://aadhum.mith.us/images/2080e82d02d62dd9840aedec01d04496",
                  "profile": "http://iiif.io/api/image/2/level0.json"
                }
              },
              "on": "http://aadhum.mith.us/mdu/062615/9/canvas"
            }
          ]
        },
        {
          "@id": "http://aadhum.mith.us/mdu/062615/10/canvas",
          "@type": "sc:Canvas",
          "label": "0010",
          "thumbnail": {
            "@id": "http://aadhum.mith.us/images/9454620d148d640daac905d9cc4f1d8c/full/421,/0/default.jpg",
            "service": {
              "@context": "http://iiif.io/api/image/2/context.json",
              "@id": "http://aadhum.mith.us/images/9454620d148d640daac905d9cc4f1d8c",
              "profile": [
                "http://iiif.io/api/image/2/level0.json",
                {
                  "qualities": [
                    "default"
                  ],
                  "formats": [
                    "jpg"
                  ]
                }
              ]
            }
          },
          "height": 4392,
          "width": 3366,
          "images": [
            {
              "@id": "http://aadhum.mith.us/mdu/062615/10/annotation",
              "@type": "oa:Annotation",
              "motivation": "sc:painting",
              "resource": {
                "@id": "http://aadhum.mith.us/images/9454620d148d640daac905d9cc4f1d8c/full/full/0/default.jpg",
                "@type": "dctypes:Image",
                "format": "image/jpeg",
                "height": 4392,
                "width": 3366,
                "service": {
                  "@context": "http://iiif.io/api/image/2/context.json",
                  "@id": "http://aadhum.mith.us/images/9454620d148d640daac905d9cc4f1d8c",
                  "profile": "http://iiif.io/api/image/2/level0.json"
                }
              },
              "on": "http://aadhum.mith.us/mdu/062615/10/canvas"
            }
          ]
        },
        {
          "@id": "http://aadhum.mith.us/mdu/062615/11/canvas",
          "@type": "sc:Canvas",
          "label": "0011",
          "thumbnail": {
            "@id": "http://aadhum.mith.us/images/e93469206d93cbe6c8c5a0bb0f65d243/full/422,/0/default.jpg",
            "service": {
              "@context": "http://iiif.io/api/image/2/context.json",
              "@id": "http://aadhum.mith.us/images/e93469206d93cbe6c8c5a0bb0f65d243",
              "profile": [
                "http://iiif.io/api/image/2/level0.json",
                {
                  "qualities": [
                    "default"
                  ],
                  "formats": [
                    "jpg"
                  ]
                }
              ]
            }
          },
          "height": 4408,
          "width": 3376,
          "images": [
            {
              "@id": "http://aadhum.mith.us/mdu/062615/11/annotation",
              "@type": "oa:Annotation",
              "motivation": "sc:painting",
              "resource": {
                "@id": "http://aadhum.mith.us/images/e93469206d93cbe6c8c5a0bb0f65d243/full/full/0/default.jpg",
                "@type": "dctypes:Image",
                "format": "image/jpeg",
                "height": 4408,
                "width": 3376,
                "service": {
                  "@context": "http://iiif.io/api/image/2/context.json",
                  "@id": "http://aadhum.mith.us/images/e93469206d93cbe6c8c5a0bb0f65d243",
                  "profile": "http://iiif.io/api/image/2/level0.json"
                }
              },
              "on": "http://aadhum.mith.us/mdu/062615/11/canvas"
            }
          ]
        },
        {
          "@id": "http://aadhum.mith.us/mdu/062615/12/canvas",
          "@type": "sc:Canvas",
          "label": "0012",
          "thumbnail": {
            "@id": "http://aadhum.mith.us/images/eb3bf84f70893c2fb3d8b9859a76c36e/full/422,/0/default.jpg",
            "service": {
              "@context": "http://iiif.io/api/image/2/context.json",
              "@id": "http://aadhum.mith.us/images/eb3bf84f70893c2fb3d8b9859a76c36e",
              "profile": [
                "http://iiif.io/api/image/2/level0.json",
                {
                  "qualities": [
                    "default"
                  ],
                  "formats": [
                    "jpg"
                  ]
                }
              ]
            }
          },
          "height": 4382,
          "width": 3374,
          "images": [
            {
              "@id": "http://aadhum.mith.us/mdu/062615/12/annotation",
              "@type": "oa:Annotation",
              "motivation": "sc:painting",
              "resource": {
                "@id": "http://aadhum.mith.us/images/eb3bf84f70893c2fb3d8b9859a76c36e/full/full/0/default.jpg",
                "@type": "dctypes:Image",
                "format": "image/jpeg",
                "height": 4382,
                "width": 3374,
                "service": {
                  "@context": "http://iiif.io/api/image/2/context.json",
                  "@id": "http://aadhum.mith.us/images/eb3bf84f70893c2fb3d8b9859a76c36e",
                  "profile": "http://iiif.io/api/image/2/level0.json"
                }
              },
              "on": "http://aadhum.mith.us/mdu/062615/12/canvas"
            }
          ]
        },
        {
          "@id": "http://aadhum.mith.us/mdu/062615/13/canvas",
          "@type": "sc:Canvas",
          "label": "0013",
          "thumbnail": {
            "@id": "http://aadhum.mith.us/images/c192a7a5d97a38fd50438e31d67b110a/full/422,/0/default.jpg",
            "service": {
              "@context": "http://iiif.io/api/image/2/context.json",
              "@id": "http://aadhum.mith.us/images/c192a7a5d97a38fd50438e31d67b110a",
              "profile": [
                "http://iiif.io/api/image/2/level0.json",
                {
                  "qualities": [
                    "default"
                  ],
                  "formats": [
                    "jpg"
                  ]
                }
              ]
            }
          },
          "height": 4396,
          "width": 3378,
          "images": [
            {
              "@id": "http://aadhum.mith.us/mdu/062615/13/annotation",
              "@type": "oa:Annotation",
              "motivation": "sc:painting",
              "resource": {
                "@id": "http://aadhum.mith.us/images/c192a7a5d97a38fd50438e31d67b110a/full/full/0/default.jpg",
                "@type": "dctypes:Image",
                "format": "image/jpeg",
                "height": 4396,
                "width": 3378,
                "service": {
                  "@context": "http://iiif.io/api/image/2/context.json",
                  "@id": "http://aadhum.mith.us/images/c192a7a5d97a38fd50438e31d67b110a",
                  "profile": "http://iiif.io/api/image/2/level0.json"
                }
              },
              "on": "http://aadhum.mith.us/mdu/062615/13/canvas"
            }
          ]
        },
        {
          "@id": "http://aadhum.mith.us/mdu/062615/14/canvas",
          "@type": "sc:Canvas",
          "label": "0014",
          "thumbnail": {
            "@id": "http://aadhum.mith.us/images/05d1962b2ae289a90fff6f61920bf48b/full/421,/0/default.jpg",
            "service": {
              "@context": "http://iiif.io/api/image/2/context.json",
              "@id": "http://aadhum.mith.us/images/05d1962b2ae289a90fff6f61920bf48b",
              "profile": [
                "http://iiif.io/api/image/2/level0.json",
                {
                  "qualities": [
                    "default"
                  ],
                  "formats": [
                    "jpg"
                  ]
                }
              ]
            }
          },
          "height": 4394,
          "width": 3370,
          "images": [
            {
              "@id": "http://aadhum.mith.us/mdu/062615/14/annotation",
              "@type": "oa:Annotation",
              "motivation": "sc:painting",
              "resource": {
                "@id": "http://aadhum.mith.us/images/05d1962b2ae289a90fff6f61920bf48b/full/full/0/default.jpg",
                "@type": "dctypes:Image",
                "format": "image/jpeg",
                "height": 4394,
                "width": 3370,
                "service": {
                  "@context": "http://iiif.io/api/image/2/context.json",
                  "@id": "http://aadhum.mith.us/images/05d1962b2ae289a90fff6f61920bf48b",
                  "profile": "http://iiif.io/api/image/2/level0.json"
                }
              },
              "on": "http://aadhum.mith.us/mdu/062615/14/canvas"
            }
          ]
        },
        {
          "@id": "http://aadhum.mith.us/mdu/062615/15/canvas",
          "@type": "sc:Canvas",
          "label": "0015",
          "thumbnail": {
            "@id": "http://aadhum.mith.us/images/50a2180db0977989e8c8724547c7564f/full/421,/0/default.jpg",
            "service": {
              "@context": "http://iiif.io/api/image/2/context.json",
              "@id": "http://aadhum.mith.us/images/50a2180db0977989e8c8724547c7564f",
              "profile": [
                "http://iiif.io/api/image/2/level0.json",
                {
                  "qualities": [
                    "default"
                  ],
                  "formats": [
                    "jpg"
                  ]
                }
              ]
            }
          },
          "height": 4403,
          "width": 3370,
          "images": [
            {
              "@id": "http://aadhum.mith.us/mdu/062615/15/annotation",
              "@type": "oa:Annotation",
              "motivation": "sc:painting",
              "resource": {
                "@id": "http://aadhum.mith.us/images/50a2180db0977989e8c8724547c7564f/full/full/0/default.jpg",
                "@type": "dctypes:Image",
                "format": "image/jpeg",
                "height": 4403,
                "width": 3370,
                "service": {
                  "@context": "http://iiif.io/api/image/2/context.json",
                  "@id": "http://aadhum.mith.us/images/50a2180db0977989e8c8724547c7564f",
                  "profile": "http://iiif.io/api/image/2/level0.json"
                }
              },
              "on": "http://aadhum.mith.us/mdu/062615/15/canvas"
            }
          ]
        },
        {
          "@id": "http://aadhum.mith.us/mdu/062615/16/canvas",
          "@type": "sc:Canvas",
          "label": "0016",
          "thumbnail": {
            "@id": "http://aadhum.mith.us/images/23ca52431a77e28c2db57cbb20aebb55/full/421,/0/default.jpg",
            "service": {
              "@context": "http://iiif.io/api/image/2/context.json",
              "@id": "http://aadhum.mith.us/images/23ca52431a77e28c2db57cbb20aebb55",
              "profile": [
                "http://iiif.io/api/image/2/level0.json",
                {
                  "qualities": [
                    "default"
                  ],
                  "formats": [
                    "jpg"
                  ]
                }
              ]
            }
          },
          "height": 4394,
          "width": 3370,
          "images": [
            {
              "@id": "http://aadhum.mith.us/mdu/062615/16/annotation",
              "@type": "oa:Annotation",
              "motivation": "sc:painting",
              "resource": {
                "@id": "http://aadhum.mith.us/images/23ca52431a77e28c2db57cbb20aebb55/full/full/0/default.jpg",
                "@type": "dctypes:Image",
                "format": "image/jpeg",
                "height": 4394,
                "width": 3370,
                "service": {
                  "@context": "http://iiif.io/api/image/2/context.json",
                  "@id": "http://aadhum.mith.us/images/23ca52431a77e28c2db57cbb20aebb55",
                  "profile": "http://iiif.io/api/image/2/level0.json"
                }
              },
              "on": "http://aadhum.mith.us/mdu/062615/16/canvas"
            }
          ]
        },
        {
          "@id": "http://aadhum.mith.us/mdu/062615/17/canvas",
          "@type": "sc:Canvas",
          "label": "0017",
          "thumbnail": {
            "@id": "http://aadhum.mith.us/images/8350970cc723cbc75712bad59c0c292c/full/422,/0/default.jpg",
            "service": {
              "@context": "http://iiif.io/api/image/2/context.json",
              "@id": "http://aadhum.mith.us/images/8350970cc723cbc75712bad59c0c292c",
              "profile": [
                "http://iiif.io/api/image/2/level0.json",
                {
                  "qualities": [
                    "default"
                  ],
                  "formats": [
                    "jpg"
                  ]
                }
              ]
            }
          },
          "height": 4384,
          "width": 3378,
          "images": [
            {
              "@id": "http://aadhum.mith.us/mdu/062615/17/annotation",
              "@type": "oa:Annotation",
              "motivation": "sc:painting",
              "resource": {
                "@id": "http://aadhum.mith.us/images/8350970cc723cbc75712bad59c0c292c/full/full/0/default.jpg",
                "@type": "dctypes:Image",
                "format": "image/jpeg",
                "height": 4384,
                "width": 3378,
                "service": {
                  "@context": "http://iiif.io/api/image/2/context.json",
                  "@id": "http://aadhum.mith.us/images/8350970cc723cbc75712bad59c0c292c",
                  "profile": "http://iiif.io/api/image/2/level0.json"
                }
              },
              "on": "http://aadhum.mith.us/mdu/062615/17/canvas"
            }
          ]
        },
        {
          "@id": "http://aadhum.mith.us/mdu/062615/18/canvas",
          "@type": "sc:Canvas",
          "label": "0018",
          "thumbnail": {
            "@id": "http://aadhum.mith.us/images/913235c0a9873305fd5a9b94fd900576/full/421,/0/default.jpg",
            "service": {
              "@context": "http://iiif.io/api/image/2/context.json",
              "@id": "http://aadhum.mith.us/images/913235c0a9873305fd5a9b94fd900576",
              "profile": [
                "http://iiif.io/api/image/2/level0.json",
                {
                  "qualities": [
                    "default"
                  ],
                  "formats": [
                    "jpg"
                  ]
                }
              ]
            }
          },
          "height": 4394,
          "width": 3368,
          "images": [
            {
              "@id": "http://aadhum.mith.us/mdu/062615/18/annotation",
              "@type": "oa:Annotation",
              "motivation": "sc:painting",
              "resource": {
                "@id": "http://aadhum.mith.us/images/913235c0a9873305fd5a9b94fd900576/full/full/0/default.jpg",
                "@type": "dctypes:Image",
                "format": "image/jpeg",
                "height": 4394,
                "width": 3368,
                "service": {
                  "@context": "http://iiif.io/api/image/2/context.json",
                  "@id": "http://aadhum.mith.us/images/913235c0a9873305fd5a9b94fd900576",
                  "profile": "http://iiif.io/api/image/2/level0.json"
                }
              },
              "on": "http://aadhum.mith.us/mdu/062615/18/canvas"
            }
          ]
        },
        {
          "@id": "http://aadhum.mith.us/mdu/062615/19/canvas",
          "@type": "sc:Canvas",
          "label": "0019",
          "thumbnail": {
            "@id": "http://aadhum.mith.us/images/557da329b13678802f742aff74547ce7/full/422,/0/default.jpg",
            "service": {
              "@context": "http://iiif.io/api/image/2/context.json",
              "@id": "http://aadhum.mith.us/images/557da329b13678802f742aff74547ce7",
              "profile": [
                "http://iiif.io/api/image/2/level0.json",
                {
                  "qualities": [
                    "default"
                  ],
                  "formats": [
                    "jpg"
                  ]
                }
              ]
            }
          },
          "height": 4396,
          "width": 3372,
          "images": [
            {
              "@id": "http://aadhum.mith.us/mdu/062615/19/annotation",
              "@type": "oa:Annotation",
              "motivation": "sc:painting",
              "resource": {
                "@id": "http://aadhum.mith.us/images/557da329b13678802f742aff74547ce7/full/full/0/default.jpg",
                "@type": "dctypes:Image",
                "format": "image/jpeg",
                "height": 4396,
                "width": 3372,
                "service": {
                  "@context": "http://iiif.io/api/image/2/context.json",
                  "@id": "http://aadhum.mith.us/images/557da329b13678802f742aff74547ce7",
                  "profile": "http://iiif.io/api/image/2/level0.json"
                }
              },
              "on": "http://aadhum.mith.us/mdu/062615/19/canvas"
            }
          ]
        },
        {
          "@id": "http://aadhum.mith.us/mdu/062615/20/canvas",
          "@type": "sc:Canvas",
          "label": "0020",
          "thumbnail": {
            "@id": "http://aadhum.mith.us/images/8705171ef132fe3553cfcbb03209ee39/full/423,/0/default.jpg",
            "service": {
              "@context": "http://iiif.io/api/image/2/context.json",
              "@id": "http://aadhum.mith.us/images/8705171ef132fe3553cfcbb03209ee39",
              "profile": [
                "http://iiif.io/api/image/2/level0.json",
                {
                  "qualities": [
                    "default"
                  ],
                  "formats": [
                    "jpg"
                  ]
                }
              ]
            }
          },
          "height": 4388,
          "width": 3384,
          "images": [
            {
              "@id": "http://aadhum.mith.us/mdu/062615/20/annotation",
              "@type": "oa:Annotation",
              "motivation": "sc:painting",
              "resource": {
                "@id": "http://aadhum.mith.us/images/8705171ef132fe3553cfcbb03209ee39/full/full/0/default.jpg",
                "@type": "dctypes:Image",
                "format": "image/jpeg",
                "height": 4388,
                "width": 3384,
                "service": {
                  "@context": "http://iiif.io/api/image/2/context.json",
                  "@id": "http://aadhum.mith.us/images/8705171ef132fe3553cfcbb03209ee39",
                  "profile": "http://iiif.io/api/image/2/level0.json"
                }
              },
              "on": "http://aadhum.mith.us/mdu/062615/20/canvas"
            }
          ]
        },
        {
          "@id": "http://aadhum.mith.us/mdu/062615/21/canvas",
          "@type": "sc:Canvas",
          "label": "0021",
          "thumbnail": {
            "@id": "http://aadhum.mith.us/images/1cd7d42388d411353935b5c02c43791b/full/423,/0/default.jpg",
            "service": {
              "@context": "http://iiif.io/api/image/2/context.json",
              "@id": "http://aadhum.mith.us/images/1cd7d42388d411353935b5c02c43791b",
              "profile": [
                "http://iiif.io/api/image/2/level0.json",
                {
                  "qualities": [
                    "default"
                  ],
                  "formats": [
                    "jpg"
                  ]
                }
              ]
            }
          },
          "height": 4404,
          "width": 3382,
          "images": [
            {
              "@id": "http://aadhum.mith.us/mdu/062615/21/annotation",
              "@type": "oa:Annotation",
              "motivation": "sc:painting",
              "resource": {
                "@id": "http://aadhum.mith.us/images/1cd7d42388d411353935b5c02c43791b/full/full/0/default.jpg",
                "@type": "dctypes:Image",
                "format": "image/jpeg",
                "height": 4404,
                "width": 3382,
                "service": {
                  "@context": "http://iiif.io/api/image/2/context.json",
                  "@id": "http://aadhum.mith.us/images/1cd7d42388d411353935b5c02c43791b",
                  "profile": "http://iiif.io/api/image/2/level0.json"
                }
              },
              "on": "http://aadhum.mith.us/mdu/062615/21/canvas"
            }
          ]
        },
        {
          "@id": "http://aadhum.mith.us/mdu/062615/22/canvas",
          "@type": "sc:Canvas",
          "label": "0022",
          "thumbnail": {
            "@id": "http://aadhum.mith.us/images/929c88ef459949f4147796fb377068ae/full/421,/0/default.jpg",
            "service": {
              "@context": "http://iiif.io/api/image/2/context.json",
              "@id": "http://aadhum.mith.us/images/929c88ef459949f4147796fb377068ae",
              "profile": [
                "http://iiif.io/api/image/2/level0.json",
                {
                  "qualities": [
                    "default"
                  ],
                  "formats": [
                    "jpg"
                  ]
                }
              ]
            }
          },
          "height": 4404,
          "width": 3364,
          "images": [
            {
              "@id": "http://aadhum.mith.us/mdu/062615/22/annotation",
              "@type": "oa:Annotation",
              "motivation": "sc:painting",
              "resource": {
                "@id": "http://aadhum.mith.us/images/929c88ef459949f4147796fb377068ae/full/full/0/default.jpg",
                "@type": "dctypes:Image",
                "format": "image/jpeg",
                "height": 4404,
                "width": 3364,
                "service": {
                  "@context": "http://iiif.io/api/image/2/context.json",
                  "@id": "http://aadhum.mith.us/images/929c88ef459949f4147796fb377068ae",
                  "profile": "http://iiif.io/api/image/2/level0.json"
                }
              },
              "on": "http://aadhum.mith.us/mdu/062615/22/canvas"
            }
          ]
        }
      ]
    }
  ]
}