{
  "@context": "http://iiif.io/api/presentation/2/context.json",
  "@id": "http://aadhum.mith.us/manifests/manifest.json",
  "@type": "sc:Manifest",
  "label": "mdu-060899",
  "sequences": [
    {
      "@type": "sc:Sequence",
      "canvases": [
        {
          "@id": "http://aadhum.mith.us/mdu/060899/1/canvas",
          "@type": "sc:Canvas",
          "label": "0001",
          "thumbnail": {
            "@id": "http://aadhum.mith.us/images/4dfcef496bb92bca341b5ed112f4359e/full/388,/0/default.jpg",
            "service": {
              "@context": "http://iiif.io/api/image/2/context.json",
              "@id": "http://aadhum.mith.us/images/4dfcef496bb92bca341b5ed112f4359e",
              "profile": [
                "http://iiif.io/api/image/2/level0.json",
                {
                  "qualities": [
                    "default"
                  ],
                  "formats": [
                    "jpg"
                  ]
                }
              ]
            }
          },
          "height": 4680,
          "width": 3104,
          "images": [
            {
              "@id": "http://aadhum.mith.us/mdu/060899/1/annotation",
              "@type": "oa:Annotation",
              "motivation": "sc:painting",
              "resource": {
                "@id": "http://aadhum.mith.us/images/4dfcef496bb92bca341b5ed112f4359e/full/full/0/default.jpg",
                "@type": "dctypes:Image",
                "format": "image/jpeg",
                "height": 4680,
                "width": 3104,
                "service": {
                  "@context": "http://iiif.io/api/image/2/context.json",
                  "@id": "http://aadhum.mith.us/images/4dfcef496bb92bca341b5ed112f4359e",
                  "profile": "http://iiif.io/api/image/2/level0.json"
                }
              },
              "on": "http://aadhum.mith.us/mdu/060899/1/canvas"
            }
          ]
        },
        {
          "@id": "http://aadhum.mith.us/mdu/060899/2/canvas",
          "@type": "sc:Canvas",
          "label": "0002",
          "thumbnail": {
            "@id": "http://aadhum.mith.us/images/b833505c956b48e6881430dfc3501070/full/388,/0/default.jpg",
            "service": {
              "@context": "http://iiif.io/api/image/2/context.json",
              "@id": "http://aadhum.mith.us/images/b833505c956b48e6881430dfc3501070",
              "profile": [
                "http://iiif.io/api/image/2/level0.json",
                {
                  "qualities": [
                    "default"
                  ],
                  "formats": [
                    "jpg"
                  ]
                }
              ]
            }
          },
          "height": 4685,
          "width": 3102,
          "images": [
            {
              "@id": "http://aadhum.mith.us/mdu/060899/2/annotation",
              "@type": "oa:Annotation",
              "motivation": "sc:painting",
              "resource": {
                "@id": "http://aadhum.mith.us/images/b833505c956b48e6881430dfc3501070/full/full/0/default.jpg",
                "@type": "dctypes:Image",
                "format": "image/jpeg",
                "height": 4685,
                "width": 3102,
                "service": {
                  "@context": "http://iiif.io/api/image/2/context.json",
                  "@id": "http://aadhum.mith.us/images/b833505c956b48e6881430dfc3501070",
                  "profile": "http://iiif.io/api/image/2/level0.json"
                }
              },
              "on": "http://aadhum.mith.us/mdu/060899/2/canvas"
            }
          ]
        },
        {
          "@id": "http://aadhum.mith.us/mdu/060899/3/canvas",
          "@type": "sc:Canvas",
          "label": "0003",
          "thumbnail": {
            "@id": "http://aadhum.mith.us/images/669a0c7c45a0c16e746cc052b5a272e3/full/387,/0/default.jpg",
            "service": {
              "@context": "http://iiif.io/api/image/2/context.json",
              "@id": "http://aadhum.mith.us/images/669a0c7c45a0c16e746cc052b5a272e3",
              "profile": [
                "http://iiif.io/api/image/2/level0.json",
                {
                  "qualities": [
                    "default"
                  ],
                  "formats": [
                    "jpg"
                  ]
                }
              ]
            }
          },
          "height": 4680,
          "width": 3096,
          "images": [
            {
              "@id": "http://aadhum.mith.us/mdu/060899/3/annotation",
              "@type": "oa:Annotation",
              "motivation": "sc:painting",
              "resource": {
                "@id": "http://aadhum.mith.us/images/669a0c7c45a0c16e746cc052b5a272e3/full/full/0/default.jpg",
                "@type": "dctypes:Image",
                "format": "image/jpeg",
                "height": 4680,
                "width": 3096,
                "service": {
                  "@context": "http://iiif.io/api/image/2/context.json",
                  "@id": "http://aadhum.mith.us/images/669a0c7c45a0c16e746cc052b5a272e3",
                  "profile": "http://iiif.io/api/image/2/level0.json"
                }
              },
              "on": "http://aadhum.mith.us/mdu/060899/3/canvas"
            }
          ]
        },
        {
          "@id": "http://aadhum.mith.us/mdu/060899/4/canvas",
          "@type": "sc:Canvas",
          "label": "0004",
          "thumbnail": {
            "@id": "http://aadhum.mith.us/images/32bc4e22fc1f73db90201665bb5a0469/full/387,/0/default.jpg",
            "service": {
              "@context": "http://iiif.io/api/image/2/context.json",
              "@id": "http://aadhum.mith.us/images/32bc4e22fc1f73db90201665bb5a0469",
              "profile": [
                "http://iiif.io/api/image/2/level0.json",
                {
                  "qualities": [
                    "default"
                  ],
                  "formats": [
                    "jpg"
                  ]
                }
              ]
            }
          },
          "height": 4680,
          "width": 3092,
          "images": [
            {
              "@id": "http://aadhum.mith.us/mdu/060899/4/annotation",
              "@type": "oa:Annotation",
              "motivation": "sc:painting",
              "resource": {
                "@id": "http://aadhum.mith.us/images/32bc4e22fc1f73db90201665bb5a0469/full/full/0/default.jpg",
                "@type": "dctypes:Image",
                "format": "image/jpeg",
                "height": 4680,
                "width": 3092,
                "service": {
                  "@context": "http://iiif.io/api/image/2/context.json",
                  "@id": "http://aadhum.mith.us/images/32bc4e22fc1f73db90201665bb5a0469",
                  "profile": "http://iiif.io/api/image/2/level0.json"
                }
              },
              "on": "http://aadhum.mith.us/mdu/060899/4/canvas"
            }
          ]
        },
        {
          "@id": "http://aadhum.mith.us/mdu/060899/5/canvas",
          "@type": "sc:Canvas",
          "label": "0005",
          "thumbnail": {
            "@id": "http://aadhum.mith.us/images/90d56d990ffbcea4ce4fd010c989799a/full/388,/0/default.jpg",
            "service": {
              "@context": "http://iiif.io/api/image/2/context.json",
              "@id": "http://aadhum.mith.us/images/90d56d990ffbcea4ce4fd010c989799a",
              "profile": [
                "http://iiif.io/api/image/2/level0.json",
                {
                  "qualities": [
                    "default"
                  ],
                  "formats": [
                    "jpg"
                  ]
                }
              ]
            }
          },
          "height": 4688,
          "width": 3104,
          "images": [
            {
              "@id": "http://aadhum.mith.us/mdu/060899/5/annotation",
              "@type": "oa:Annotation",
              "motivation": "sc:painting",
              "resource": {
                "@id": "http://aadhum.mith.us/images/90d56d990ffbcea4ce4fd010c989799a/full/full/0/default.jpg",
                "@type": "dctypes:Image",
                "format": "image/jpeg",
                "height": 4688,
                "width": 3104,
                "service": {
                  "@context": "http://iiif.io/api/image/2/context.json",
                  "@id": "http://aadhum.mith.us/images/90d56d990ffbcea4ce4fd010c989799a",
                  "profile": "http://iiif.io/api/image/2/level0.json"
                }
              },
              "on": "http://aadhum.mith.us/mdu/060899/5/canvas"
            }
          ]
        },
        {
          "@id": "http://aadhum.mith.us/mdu/060899/6/canvas",
          "@type": "sc:Canvas",
          "label": "0006",
          "thumbnail": {
            "@id": "http://aadhum.mith.us/images/225f34e9bfe16f05415c3ae1870bf5ba/full/388,/0/default.jpg",
            "service": {
              "@context": "http://iiif.io/api/image/2/context.json",
              "@id": "http://aadhum.mith.us/images/225f34e9bfe16f05415c3ae1870bf5ba",
              "profile": [
                "http://iiif.io/api/image/2/level0.json",
                {
                  "qualities": [
                    "default"
                  ],
                  "formats": [
                    "jpg"
                  ]
                }
              ]
            }
          },
          "height": 4691,
          "width": 3100,
          "images": [
            {
              "@id": "http://aadhum.mith.us/mdu/060899/6/annotation",
              "@type": "oa:Annotation",
              "motivation": "sc:painting",
              "resource": {
                "@id": "http://aadhum.mith.us/images/225f34e9bfe16f05415c3ae1870bf5ba/full/full/0/default.jpg",
                "@type": "dctypes:Image",
                "format": "image/jpeg",
                "height": 4691,
                "width": 3100,
                "service": {
                  "@context": "http://iiif.io/api/image/2/context.json",
                  "@id": "http://aadhum.mith.us/images/225f34e9bfe16f05415c3ae1870bf5ba",
                  "profile": "http://iiif.io/api/image/2/level0.json"
                }
              },
              "on": "http://aadhum.mith.us/mdu/060899/6/canvas"
            }
          ]
        },
        {
          "@id": "http://aadhum.mith.us/mdu/060899/7/canvas",
          "@type": "sc:Canvas",
          "label": "0007",
          "thumbnail": {
            "@id": "http://aadhum.mith.us/images/d1cd385569ed134441b1f9d693883ddb/full/388,/0/default.jpg",
            "service": {
              "@context": "http://iiif.io/api/image/2/context.json",
              "@id": "http://aadhum.mith.us/images/d1cd385569ed134441b1f9d693883ddb",
              "profile": [
                "http://iiif.io/api/image/2/level0.json",
                {
                  "qualities": [
                    "default"
                  ],
                  "formats": [
                    "jpg"
                  ]
                }
              ]
            }
          },
          "height": 4705,
          "width": 3104,
          "images": [
            {
              "@id": "http://aadhum.mith.us/mdu/060899/7/annotation",
              "@type": "oa:Annotation",
              "motivation": "sc:painting",
              "resource": {
                "@id": "http://aadhum.mith.us/images/d1cd385569ed134441b1f9d693883ddb/full/full/0/default.jpg",
                "@type": "dctypes:Image",
                "format": "image/jpeg",
                "height": 4705,
                "width": 3104,
                "service": {
                  "@context": "http://iiif.io/api/image/2/context.json",
                  "@id": "http://aadhum.mith.us/images/d1cd385569ed134441b1f9d693883ddb",
                  "profile": "http://iiif.io/api/image/2/level0.json"
                }
              },
              "on": "http://aadhum.mith.us/mdu/060899/7/canvas"
            }
          ]
        }
      ]
    }
  ]
}